precylinderocr/__init__.py
precylinderocr/memory.py
precylinderocr-0.0.9.dist-info/LICENSE
precylinderocr-0.0.9.dist-info/METADATA
precylinderocr-0.0.9.dist-info/WHEEL
precylinderocr-0.0.9.dist-info/top_level.txt
precylinderocr-0.0.9.dist-info/RECORD
