Metadata-Version: 2.1
Name: precylinderocr
Version: 0.0.9
Summary: precylinder  ocr package
Home-page: https://github.com/Codebugged-Research/precylinderocr
Author: Codebugged-Research
Author-email: thecodebugged@gmail.com
License: MIT
Classifier: Intended Audience :: Developers
Classifier: Operating System :: OS Independent
Classifier: Natural Language :: Chinese (Simplified)
Classifier: Programming Language :: Python :: 3.6
Classifier: Topic :: Utilities
Classifier: Programming Language :: Python :: 3.7
Classifier: Topic :: Utilities
Classifier: Programming Language :: Python :: 3.8
Classifier: Topic :: Utilities
Requires-Python: >=3.6
License-File: LICENSE
Requires-Dist: paddleocr
Requires-Dist: getmac
